djaport/__init__.py
djaport/mixins.py
djaport/runner.py
djaport/templates/report.html
djaport-0.1.0.dist-info/LICENSE
djaport-0.1.0.dist-info/METADATA
djaport-0.1.0.dist-info/WHEEL
djaport-0.1.0.dist-info/top_level.txt
djaport-0.1.0.dist-info/RECORD
